{
	"airhorn": 
	{
		"category": "player",
		"sounds": 
		[
			"dab:airhorn"
		],
		"subtitle": "airhorn"
 	},

	"records.mlgcancan":
	{
		"category": "record",
		"sounds": 
		[
          {
            "name": "dab:mlgcancan",
            "stream": true
          }
		],
		"subtitle": "mlgcancan"
 	},
    "sadairhorn":
    {
        "category": "player",
        "sounds":
        [
          {
            "name": "dab:sadairhorn",
            "stream": true
          }
        ],
      "subtitle": "sadairhorn"
    },
	"specialcobblestone":
	{
		"category": "block",
		"sounds":
        [
          {
            "name": "dab:specialcobblestone"
          }
        ],
		"subtitle": "specialcobblestone"
	}
}